sim_racing_tools
