Metadata-Version: 2.1
Name: sim-racing-tools
Version: 2021.6.2
Summary: A collection of tools to make sim-racing more fun
Home-page: https://github.com/zephyrj/sim-racing-tools
Author: zephyrj
Author-email: zephyrj@protonmail.com
License: UNKNOWN
Download-URL: https://github.com/zephyrj/sim-racing-tools/archive/refs/tags/2021.6.2.tar.gz
Project-URL: Bug Tracker, https://github.com/zephyrj/sim-racing-tools/issues
Keywords: Assetto Corsa,Automation,Sim Racing
Platform: UNKNOWN
Classifier: Programming Language :: Python :: 3
Classifier: Development Status :: 4 - Beta
Classifier: License :: OSI Approved :: GNU General Public License v3 or later (GPLv3+)
Classifier: Operating System :: OS Independent
Requires-Python: >=3.6
